fast_seeker/__init__.py
fast_seeker/py.typed
fast_seeker/contrib/__init__.py
fast_seeker/contrib/beanie/__init__.py
fast_seeker/contrib/beanie/filtering.py
fast_seeker/contrib/beanie/pagination.py
fast_seeker/contrib/beanie/sorting.py
fast_seeker/contrib/django/__init__.py
fast_seeker/contrib/django/filtering.py
fast_seeker/contrib/django/pagination.py
fast_seeker/contrib/django/sorting.py
fast_seeker/core/__init__.py
fast_seeker/core/base.py
fast_seeker/core/filtering.py
fast_seeker/core/pagination.py
fast_seeker/core/sorting.py
fast_seeker-0.1.0.dist-info/METADATA
fast_seeker-0.1.0.dist-info/WHEEL
fast_seeker-0.1.0.dist-info/RECORD
